test.py
template_align/__init__.py
template_align/main.py
template_align-0.0.2.dist-info/LICENSE
template_align-0.0.2.dist-info/METADATA
template_align-0.0.2.dist-info/WHEEL
template_align-0.0.2.dist-info/entry_points.txt
template_align-0.0.2.dist-info/top_level.txt
template_align-0.0.2.dist-info/RECORD
