Metadata-Version: 2.2
Name: template_align
Version: 0.0.2
Summary: Align images based on a template
Author-email: Mathias Zinnen <mathias.zinnen@gmail.com>
License:                     GNU GENERAL PUBLIC LICENSE
Project-URL: Homepage, https://github.com/mathiaszinnen/template-align
Classifier: Programming Language :: Python :: 3
Classifier: Operating System :: OS Independent
License-File: LICENSE
Requires-Dist: opencv-python
Requires-Dist: tqdm
Requires-Dist: scikit-image
